adanet/__init__.py
adanet/version.py
adanet/autoensemble/__init__.py
adanet/autoensemble/common.py
adanet/autoensemble/estimator.py
adanet/core/__init__.py
adanet/core/architecture.py
adanet/core/candidate.py
adanet/core/ensemble_builder.py
adanet/core/estimator.py
adanet/core/eval_metrics.py
adanet/core/evaluator.py
adanet/core/iteration.py
adanet/core/report_accessor.py
adanet/core/report_materializer.py
adanet/core/summary.py
adanet/core/timer.py
adanet/core/tpu_estimator.py
adanet/distributed/__init__.py
adanet/distributed/devices.py
adanet/distributed/placement.py
adanet/ensemble/__init__.py
adanet/ensemble/ensembler.py
adanet/ensemble/mean.py
adanet/ensemble/strategy.py
adanet/ensemble/weighted.py
adanet/examples/__init__.py
adanet/examples/simple_dnn.py
adanet/replay/__init__.py
adanet/subnetwork/__init__.py
adanet/subnetwork/generator.py
adanet/subnetwork/report.py
adanet/tf_compat/__init__.py
adanet-0.9.0.dist-info/LICENSE.txt
adanet-0.9.0.dist-info/METADATA
adanet-0.9.0.dist-info/WHEEL
adanet-0.9.0.dist-info/top_level.txt
adanet-0.9.0.dist-info/RECORD
